beneficiary/__init__.py
beneficiary/admin.py
beneficiary/apps.py
beneficiary/models.py
beneficiary/serializers.py
beneficiary/tests.py
beneficiary/urls.py
beneficiary/views.py
beneficiary/migrations/0001_initial.py
beneficiary/migrations/0002_auto_20191221_1611.py
beneficiary/migrations/0003_auto_20191221_1619.py
beneficiary/migrations/__init__.py
quotation/__init__.py
quotation/admin.py
quotation/apps.py
quotation/models.py
quotation/serializers.py
quotation/tests.py
quotation/urls.py
quotation/views.py
quotation/migrations/0001_initial.py
quotation/migrations/0002_auto_20191221_1341.py
quotation/migrations/0003_auto_20191221_1342.py
quotation/migrations/0004_auto_20191221_1353.py
quotation/migrations/__init__.py
sender/__init__.py
sender/admin.py
sender/apps.py
sender/models.py
sender/serializers.py
sender/tests.py
sender/urls.py
sender/views.py
sender/migrations/0001_initial.py
sender/migrations/0002_auto_20191221_1611.py
sender/migrations/__init__.py
thunes/APIAccessGrant.py
thunes/__init__.py
thunes/urls.py
thunes/wsgi.py
thunes/settings/__init__.py
thunes/settings/base.py
thunes/settings/develop.py
thunes/settings/product.py
thunes-0.31.data/scripts/manage.py
transaction/__init__.py
transaction/admin.py
transaction/apps.py
transaction/models.py
transaction/serializers.py
transaction/tests.py
transaction/urls.py
transaction/views.py
transaction/migrations/0001_initial.py
transaction/migrations/0002_auto_20191221_1340.py
transaction/migrations/0003_auto_20191221_1643.py
transaction/migrations/0004_auto_20191221_1656.py
transaction/migrations/0005_auto_20191221_1656.py
transaction/migrations/0006_auto_20191221_1659.py
transaction/migrations/0007_transactionsenderbeneficiary.py
transaction/migrations/0008_delete_transactionsenderbeneficiary.py
transaction/migrations/__init__.py
thunes-0.31.dist-info/METADATA
thunes-0.31.dist-info/WHEEL
thunes-0.31.dist-info/entry_points.txt
thunes-0.31.dist-info/top_level.txt
thunes-0.31.dist-info/RECORD
